README.rst
setup.py
./cladecompare.py
./cladereport.py
./cladeweb.py
CladeCompare.egg-info/PKG-INFO
CladeCompare.egg-info/SOURCES.txt
CladeCompare.egg-info/dependency_links.txt
CladeCompare.egg-info/requires.txt
CladeCompare.egg-info/top_level.txt
cladecomparelib/__init__.py
cladecomparelib/ancestrallrt.py
cladecomparelib/core.py
cladecomparelib/entropy.py
cladecomparelib/gtest.py
cladecomparelib/jsd.py
cladecomparelib/pairlogo.py
cladecomparelib/phospho.py
cladecomparelib/pmlscript.py
cladecomparelib/report.py
cladecomparelib/shared.py
cladecomparelib/sp.py
cladecomparelib/urn.py