Metadata-Version: 1.0
Name: CladeCompare
Version: 0.2
Summary: Test for sites of contrasting conservation between gene clades.
Home-page: http://github.com/etal/cladecompare
Author: Eric Talevich
Author-email: etal@uga.edu
License: UNKNOWN
Platform: UNKNOWN
